example/__init__.py
example/script.py
excel2py_lib-1.0.1.dist-info/LICENSE
excel2py_lib-1.0.1.dist-info/METADATA
excel2py_lib-1.0.1.dist-info/WHEEL
excel2py_lib-1.0.1.dist-info/top_level.txt
excel2py_lib-1.0.1.dist-info/RECORD
